[
  [
    {
      "dia": "lunes",
      "musculo": "gluteos y femorales",
      "ejercicios": {
        "gluteos y femorales": [
          {
            "orden": 1,
            "ejercicio": "elevación de cadera",
            "cantidad": "12",
            "repeticiones": 4,
            "musculo": "gluteo mayor, medio y menor",
            "url_demostracion": "https://www.myprotein.es/thezone/entrenamiento/hip-thrust-gluteos-mas-grandes/"
          },
          {
            "orden": 2,
            "ejercicio": "peso muerto",
            "repeticiones": 4,
            "cantidad": "10 o 12",
            "descripcion": "",
            "musculo": "femoral y gluteo",
            "url_demostracion": "https://www.myprotein.es/thezone/entrenamiento/peso-muerto-rumano/"
          },
          {
            "orden": 3,
            "ejercicio": "patada de gluteos",
            "repeticiones": 4,
            "cantidad": "12",
            "url_demostracion": "https://www.youtube.com/shorts/B9Fqo0KqeWc"
          },
          {
            "orden": 4,
            "ejercicio": "maquina de femorales acostado",
            "repeticiones": 4,
            "descripcion": "",
            "cantidad": "10 o 12",
            "musculo": "femoral",
            "url_demostracion": "https://www.myprotein.es/thezone/entrenamiento/curl-femoral-tumbado/"
          },
          {
            "orden": 4,
            "ejercicio": "Alguno de gemelos",
            "descripcion": "40 en total, 10 de cada uno",
            "cantidad": "50",
            "repeticiones": 4,
            "musculo": "gemelos"
          }
        ]
      }
    },
    {
      "dia": "martes",
      "musculo": "pecho y triceps",
      "ejercicios": {
        "pecho": [
          {
            "orden": 1,
            "ejercicio": "Banco inclinado barra",
            "cantidad": "12",
            "descripcion": "",
            "repeticiones": 4,
            "musculo": "Pectoral superior",
            "url_demostracion": "https://www.myprotein.es/thezone/entrenamiento/press-de-banca-inclinado/"
          },
          {
            "orden": 2,
            "ejercicio": "Banco plano barra",
            "repeticiones": 4,
            "cantidad": "10 o 12",
            "descripcion": "",
            "musculo": "pectoral medio",
            "url_demostracion": "https://www.myprotein.es/thezone/entrenamiento/como-utilizar-correctamente-el-press-de-banca/"
          },
          {
            "orden": 3,
            "ejercicio": "Maquina mariposa o apertura",
            "repeticiones": 4,
            "cantidad": "12",
            "musculo": "pectoral inferior"
          }
        ],
        "triceps": [
          {
            "orden": 1,
            "ejercicio": "Fondos o soga en polea de frente.",
            "repeticiones": 4,
            "cantidad": "12",
            "musculo": "Cabeza larga, lateral y media.",
            "url_demostracion": "https://www.myprotein.es/thezone/entrenamiento/fondos-de-triceps/"
          },
          {
            "orden": 2,
            "ejercicio": "Polea con Barra Recta (Agarre Normal e Inverso)",
            "cantidad": "12",
            "repeticiones": 4,
            "musculo": "cabeza larga y lateral, agarre inverso cabeza media.",
            "url_demostracion": "https://www.youtube.com/shorts/S1mPrwz8JWI"
          },
          {
            "orden": 3,
            "ejercicio": "Extensión de tríceps por encima de la cabeza con mancuerna o soga",
            "repeticiones": 4,
            "cantidad": "12",
            "musculo": "Cabeza larga del tríceps",
            "url_demostracion": "https://www.youtube.com/watch?v=-paLAzl68WU&ab_channel=FitKamp"
          }
        ]
      }
    },
    {
      "dia": "miercoles",
      "musculo": "cuadriceps",
      "ejercicios": {
        "piernas": [
          {
            "orden": 1,
            "ejercicio": "sentadilla libre",
            "cantidad": "10 o 12",
            "descripcion": "",
            "repeticiones": 4,
            "musculo": "cuádripcep",
            "url_demostracion": "https://www.myprotein.es/thezone/entrenamiento/como-hacer-una-sentadilla-perfecta/"
          },
          {
            "orden": 2,
            "ejercicio": "estocada bulgara espalda recta",
            "repeticiones": 4,
            "descripcion": "",
            "cantidad": "50",
            "musculo": "cuadriceps"
          },
          {
            "orden": 3,
            "ejercicio": "sillon de cuadriceps",
            "descripcion": "",
            "repeticiones": 4,
            "cantidad": "12",
            "musculo": "cuadricep",
            "url_demostracion": "https://www.myprotein.es/thezone/entrenamiento/extension-de-cuadriceps/"
          },
          {
            "orden": 4,
            "ejercicio": "Alguno de gemelos",
            "descripcion": "40 en total, 10 de cada uno",
            "cantidad": "50",
            "repeticiones": 4,
            "musculo": "gemelos"
          }
        ]
      }
    },
    {
      "dia": "jueves",
      "musculo": "espalda y biceps",
      "ejercicios": {
        "espalda": [
          {
            "orden": 1,
            "ejercicio": "dominadas o barra al pecho",
            "cantidad": "12",
            "repeticiones": 4,
            "musculo": "dorsal y dorsal mayor, entre otros.",
            "url_demostracion": "https://www.myprotein.es/thezone/entrenamiento/consejos-dominadas/"
          },
          {
            "orden": 2,
            "ejercicio": "remo con barra prono",
            "repeticiones": 4,
            "cantidad": "12",
            "musculo": "dorsales, traprecios medios e inferiores, romboides",
            "url_demostracion": "https://www.myprotein.es/thezone/entrenamiento/remo-inclinado-con-barra-beneficios-tecnica/"
          },
          {
            "orden": 3,
            "ejercicio": "remo bajo en polea",
            "repeticiones": 4,
            "cantidad": "12",
            "musculo": "dorsales, trapecios medios y romboides",
            "url_demostracion": "https://www.myprotein.es/thezone/entrenamiento/remo-en-polea-baja-sentado/"
          },
          {
            "orden": 4,
            "ejercicio": "pullover",
            "repeticiones": 4,
            "cantidad": "12",
            "musculo": "dorsales",
            "url_demostracion": "https://www.myprotein.es/thezone/entrenamiento/pullover-ejercicios-pecho-espalda/"
          },
          {
            "orden": 5,
            "ejercicio": "encogimientos",
            "repeticiones": 4,
            "cantidad": "12",
            "musculo": "trapecios superiores",
            "url_demostracion": "https://www.myprotein.es/thezone/entrenamiento/encogimiento-de-hombros/|"
          }
        ],
        "biceps": [
          {
            "orden": 1,
            "ejercicio": "curl con barra recta agarre neutro",
            "repeticiones": 4,
            "cantidad": "21",
            "musculo": "cabeza corta del bicep",
            "url_demostracion": "https://www.youtube.com/shorts/veOoIkW6Spw"
          },
          {
            "orden": 2,
            "ejercicio": "curl con mancuernas alterno en banco inclinado",
            "repeticiones": 4,
            "cantidad": "12",
            "musculo": "cabeza larga del bicep",
            "url_demostracion": "https://www.youtube.com/watch?v=0XVZInuV6mY&ab_channel=ToniLloret"
          },
          {
            "orden": 3,
            "ejercicio": "curl martillo con mancuernas",
            "cantidad": "12",
            "repeticiones": 4,
            "musculo": "biceps braquial",
            "url_demostracion": null
          }
        ]
      }
    },
    {
      "dia": "viernes",
      "musculo": "hombos",
      "ejercicios": {
        "hombros": [
          {
            "orden": 1,
            "ejercicio": "press con barra parado",
            "cantidad": "12",
            "repeticiones": 4
          },
          {
            "orden": 2,
            "ejercicio": "vuelos laterales",
            "descripcion": "",
            "repeticiones": 4,
            "cantidad": "10 o 12"
          },
          {
            "orden": 3,
            "ejercicio": "posterior con polea alta",
            "repeticiones": 4,
            "cantidad": "12"
          }
        ]
      }
    },
    {
      "dia": "Lunes, miercoles y viernes",
      "musculo": "abdominales",
      "descripcion": "se realiza al finalizar las rutinas de los lunes, miercoles y viernes, es todo de corrido siendo esto una rutina de 11 minutos",
      "url_demostracion": "https://www.youtube.com/shorts/SnXqb26qpYM",
      "ejercicios": {
        "abdominales": [
          {
            "orden": 1,
            "ejercicio": "Abdominales cortitos",
            "tiempo": "1 minuto",
            "musculo": "Parte superior del recto abdominal"
          },
          {
            "orden": 2,
            "ejercicio": "Plancha",
            "tiempo": "1 minuto",
            "musculo": "Recto abdominal, oblicuos, transverso del abdomen y zona lumbar"
          },
          {
            "orden": 3,
            "ejercicio": "Abdominales bicicleta",
            "tiempo": "1 minuto",
            "musculo": "Recto abdominal y oblicuos"
          },
          {
            "orden": 4,
            "ejercicio": "Descanso",
            "tiempo": "1 minuto",
            "musculo": "Recuperación muscular"
          },
          {
            "orden": 5,
            "ejercicio": "Elevación de pierna",
            "tiempo": "1 minuto",
            "musculo": "Parte inferior del recto abdominal y flexores de la cadera"
          },
          {
            "orden": 6,
            "ejercicio": "Toques de talón",
            "tiempo": "1 minuto",
            "musculo": "Oblicuos"
          },
          {
            "orden": 7,
            "ejercicio": "Espinales",
            "tiempo": "1 minuto",
            "musculo": "Zona lumbar y core posterior"
          },
          {
            "orden": 8,
            "ejercicio": "Descanso",
            "tiempo": "1 minuto",
            "musculo": "Recuperación muscular"
          },
          {
            "orden": 9,
            "ejercicio": "Plancha dinámica",
            "tiempo": "1 minuto",
            "musculo": "Transverso del abdomen, recto abdominal y estabilizadores de los hombros"
          },
          {
            "orden": 10,
            "ejercicio": "Abdominales cortitos",
            "tiempo": "1 minuto",
            "musculo": "Parte superior del recto abdominal"
          },
          {
            "orden": 11,
            "ejercicio": "Barquito",
            "tiempo": "1 minuto",
            "musculo": "Core completo: recto abdominal, oblicuos, transverso del abdomen y flexores de la cadera"
          }
        ]
      }
    }
  ]
]
